LICENSE
MANIFEST.in
README.md
demo.py
requirements.txt
setup.cfg
setup.py
filestruct/__init__.py
filestruct/document.py
filestruct/loader.py
filestruct.egg-info/PKG-INFO
filestruct.egg-info/SOURCES.txt
filestruct.egg-info/dependency_links.txt
filestruct.egg-info/requires.txt
filestruct.egg-info/top_level.txt