Metadata-Version: 2.1
Name: filestruct
Version: 0.2
Summary: A python package to structure files using visual and style informations
Home-page: https://github.com/ixalodecte/filestruct
Download-URL: https://github.com/ixalodecte/filestruct/archive/refs/tags/v0.2-alpha.tar.gz
Author: léo DECHAUMET
Author-email: leo_dechaumet_research@pm.me
License: GPLv3+
Keywords: pdf,parser,layout-analysis
Classifier: Development Status :: 3 - Alpha
Classifier: Intended Audience :: Developers
Classifier: Intended Audience :: Science/Research
Classifier: Topic :: Utilities
Classifier: Topic :: Text Processing
Classifier: License :: OSI Approved :: GNU General Public License v3 or later (GPLv3+)
Classifier: Programming Language :: Python :: 3
License-File: LICENSE
Requires-Dist: pandas
Requires-Dist: numpy
Requires-Dist: PyMuPDF
